good_coder/__init__.py
good_coder/toolkit.py
good_coder-0.1.0.dist-info/LICENSE
good_coder-0.1.0.dist-info/METADATA
good_coder-0.1.0.dist-info/WHEEL
good_coder-0.1.0.dist-info/RECORD
